vnpy_extra/__init__.py
vnpy_extra/config.py
vnpy_extra/constants.py
vnpy_extra/logging.py
vnpy_extra/backtest/__init__.py
vnpy_extra/backtest/commons.py
vnpy_extra/backtest/cta_strategy/__init__.py
vnpy_extra/backtest/cta_strategy/engine.py
vnpy_extra/backtest/cta_strategy/run.py
vnpy_extra/backtest/cta_strategy/template.py
vnpy_extra/backtest/maintain/__init__.py
vnpy_extra/backtest/maintain/backtest_from_tb_xml.py
vnpy_extra/backtest/maintain/strategy_stats.py
vnpy_extra/backtest/maintain/track_performance.py
vnpy_extra/backtest/portfolio_strategy/__init__.py
vnpy_extra/backtest/portfolio_strategy/engine.py
vnpy_extra/backtest/portfolio_strategy/run.py
vnpy_extra/backtest/portfolio_strategy/template.py
vnpy_extra/db/__init__.py
vnpy_extra/db/backtest_strategy_stats.py
vnpy_extra/db/backup.py
vnpy_extra/db/export_data.py
vnpy_extra/db/export_strategy_setting.py
vnpy_extra/db/import_data.py
vnpy_extra/db/import_save_failed.py
vnpy_extra/db/import_strategy_data.py
vnpy_extra/db/import_strategy_setting.py
vnpy_extra/db/md_reversion_rights.py
vnpy_extra/db/orm.py
vnpy_extra/db/utils.py
vnpy_extra/db/tb/__init__.py
vnpy_extra/db/tb/import_tb_param_xml.py
vnpy_extra/db/tick_data/__init__.py
vnpy_extra/db/tick_data/options/__init__.py
vnpy_extra/db/tick_data/options/fix_exch_bug.py
vnpy_extra/db/tick_data/options/load_gtja_options_tick_data.py
vnpy_extra/pm/__init__.py
vnpy_extra/pm/by_json.py
vnpy_extra/pm/clone.py
vnpy_extra/pm/optimization.py
vnpy_extra/pm/plot.py
vnpy_extra/report/__init__.py
vnpy_extra/report/collector.py
vnpy_extra/report/data_available_check.py
vnpy_extra/report/generate_md.py
vnpy_extra/report/monitor.py
vnpy_extra/utils/__init__.py
vnpy_extra/utils/cta_signal.py
vnpy_extra/utils/data.py
vnpy_extra/utils/enhancement.py
vnpy_extra/utils/exception.py
vnpy_extra/utils/exit_cta_signal.py
vnpy_extra/utils/factor.py
vnpy_extra/utils/func.py
vnpy_extra/utils/get_email.py
vnpy_extra/utils/param_opt_result.py
vnpy_extra/utils/send_email.py
vnpy_extra-0.8.20211220.0.dist-info/METADATA
vnpy_extra-0.8.20211220.0.dist-info/WHEEL
vnpy_extra-0.8.20211220.0.dist-info/top_level.txt
vnpy_extra-0.8.20211220.0.dist-info/RECORD
