Metadata-Version: 2.1
Name: vnpy-extra
Version: 0.8.20211220.0
Summary: 基于VNPY进行功能拓展
Home-page: https://github.com/IBATS/vnpy_extra
Author: MG
Author-email: mmmaaaggg@163.com
License: UNKNOWN
Platform: UNKNOWN
Classifier: Programming Language :: Python :: 3 :: Only
Classifier: Programming Language :: Python :: 3.7
Classifier: Operating System :: Microsoft :: Windows
Classifier: Operating System :: Unix
Classifier: Operating System :: POSIX
Classifier: License :: OSI Approved :: MIT License
Classifier: Development Status :: 5 - Production/Stable
Classifier: Environment :: No Input/Output (Daemon)
Classifier: Intended Audience :: Developers
Classifier: Natural Language :: Chinese (Simplified)
Classifier: Topic :: Software Development
Requires-Python: >=3.6
Requires-Dist: IBATS-Utils (>=1.20211214.0)
Requires-Dist: IBATS-Common (>=0.20.11)
Requires-Dist: psutil (>=5.7.2)
Requires-Dist: kaleido (>=0.0.3)
Requires-Dist: openpyxl (>=3.0.5)
Requires-Dist: xlwt (>=1.3.0)
Requires-Dist: tqdm (>=4.51.0)
Requires-Dist: peewee (>=3.13.3)
Requires-Dist: mysql-connector-python (>=8.0.22)
Requires-Dist: cvxpy (>=1.1.13)
Requires-Dist: cvxopt (>=1.2.6)
Requires-Dist: opencv-python (>=4.5.3)
Requires-Dist: pyportfolioopt (>=1.4.2)
Requires-Dist: numba (>=0.52.0)
Requires-Dist: scikit-learn (>=0.24.2)
